scmmd/__init__.py
scmmd/__main__.py
scmmd/mmd_ad.py
scmmd-0.1.0.dist-info/LICENSE
scmmd-0.1.0.dist-info/METADATA
scmmd-0.1.0.dist-info/WHEEL
scmmd-0.1.0.dist-info/entry_points.txt
scmmd-0.1.0.dist-info/top_level.txt
scmmd-0.1.0.dist-info/RECORD
