Metadata-Version: 2.1
Name: scmmd
Version: 0.1.0
Summary: Maximum mean discrepancy comparisons single cell profiles
Home-page: http://github.com/calico/scmmd
Author: Jacob C. Kimmel
Author-email: jacobkimmel@gmail.com
License: Apache
Platform: UNKNOWN
Classifier: Environment :: Console
Classifier: Intended Audience :: Science/Research
Classifier: Topic :: Scientific/Engineering :: Bio-Informatics
Requires-Python: >=3.6
Requires-Dist: torch (>=1.2.0)
Requires-Dist: anndata (>=0.6.22.post1)
Requires-Dist: scanpy (>=1.4)
Requires-Dist: numpy (>=1.17.4)
Requires-Dist: pandas (>=0.23.4)
Requires-Dist: tqdm (>=4.35.0)
Requires-Dist: torch-two-sample (>=0.1)
